ipyfilechooser/__init__.py
ipyfilechooser/errors.py
ipyfilechooser/filechooser.py
ipyfilechooser/utils.py
ipyfilechooser-0.6.0.dist-info/LICENSE
ipyfilechooser-0.6.0.dist-info/METADATA
ipyfilechooser-0.6.0.dist-info/WHEEL
ipyfilechooser-0.6.0.dist-info/top_level.txt
ipyfilechooser-0.6.0.dist-info/RECORD
