Metadata-Version: 2.1
Name: ipyfilechooser
Version: 0.6.0
Summary: Python file chooser widget for use in Jupyter/IPython in conjunction with ipywidgets
Home-page: https://github.com/crahan/ipyfilechooser
Author: Thomas Bouve (@crahan)
Author-email: crahan@n00.be
License: MIT
Platform: UNKNOWN
Classifier: Programming Language :: Python :: 3
Classifier: License :: OSI Approved :: MIT License
Classifier: Operating System :: OS Independent
Classifier: Development Status :: 5 - Production/Stable
Classifier: Intended Audience :: Developers
